TAILab/TAILab.py
TAILab/__init__.py
TAILab-0.0.1.dist-info/LICENSE
TAILab-0.0.1.dist-info/METADATA
TAILab-0.0.1.dist-info/WHEEL
TAILab-0.0.1.dist-info/top_level.txt
TAILab-0.0.1.dist-info/RECORD
