Metadata-Version: 2.1
Name: TAILab
Version: 0.0.1
Summary: TAILab = T.+AI+Lab
Home-page: https://github.com/tqthooo2021/Create-Own-Python-Package
Author: TAILab
Author-email: tqthooo2021@163.com
License: UNKNOWN
Platform: UNKNOWN
Classifier: Programming Language :: Python :: 3
Classifier: License :: OSI Approved :: MIT License
Classifier: Operating System :: OS Independent
License-File: LICENSE
Requires-Dist: pandas
Requires-Dist: matplotlib
Requires-Dist: numpy
Requires-Dist: scipy
Requires-Dist: pandas-profiling
Requires-Dist: folium
Requires-Dist: seaborn
